[{"Ways": [1508, -9, 22], "Nodes": [1862, -6, 196], "Relations": [522, -4, 1]}, {"amenity": {"parking": [1402, -4, 1]}, "surface": {"*": [1154, 72, 1]}, "ele": {"*": [539, -5, 1]}, "place": {"*": [952, 0, 1], "village": [640, -4, 1]}, "boundary": {"*": [400, 4, 2]}, "landuse": {"*": [884, -11, 1]}, "highway": {"streets|road;service;pedestrian;living_street;residential;unclassified;tertiary;secondary_link;secondary;primary_link;primary;trunk_link;trunk;motorway_link;motorway;bus_guideway": [1498, -45, 11], "footway": [427, 0, 8]}}]