[{"Ways": [402, -2, 721], "Nodes": [507, -2, 6277], "Relations": [585, -6, 2]}, {"building": {"yes": [215, -2, 315], "*": [219, -2, 315]}, "bridge": {"*": [477, 1, 8]}, "amenity": {"drinking_water": [405, -1, 2], "waste_basket": [18, -1, 14], "bench": [34, 3, 29], "school": [726, 4, 1], "parking": [325, 0, 18]}, "maxspeed": {"*": [292, 1, 10]}, "barrier": {"*": [274, -1, 12]}, "tunnel": {"*": [680, 1, 1]}, "wheelchair": {"*": [113, 10, 3]}, "surface": {"*": [78, -1, 221]}, "lit": {"*": [68, -1, 16]}, "width": {"*": [157, 5, 14]}, "place": {"*": [1397, 0, 1]}, "leisure": {"park": [161, 1, 7], "playground": [373, -2, 1], "pitch": [512, -4, 1]}, "waterway": {"*": [655, 292, 2]}, "landuse": {"residential": [452, -4, 1], "*": [523, 22, 9], "meadow": [250, -1, 1]}, "tourism": {"*": [279, -1, 13]}, "highway": {"crossing": [122, -5, 10], "stop": [71, 1, 2], "streets|road;service;pedestrian;living_street;residential;unclassified;tertiary;secondary_link;secondary;primary_link;primary;trunk_link;trunk;motorway_link;motorway;bus_guideway": [491, -2, 214], "footway": [404, 0, 13], "path": [231, -6, 40]}}]