[{"Ways": [146, -1, 2657], "Nodes": [437, -3, 5625], "Relations": [121, -4, 27]}, {"shop": {"*": [63, 0, 44]}, "bridge": {"*": [69, -1, 143]}, "amenity": {"fast_food": [24, 1, 8], "drinking_water": [101, -3, 14], "school": [56, 2, 15], "bar": [572, -5, 1], "restaurant": [21, 0, 46], "post_box": [39, 0, 4], "hospital": [37, 0, 6], "telephone": [33, 0, 9], "pub": [85, -1, 3], "pharmacy": [28, 0, 15], "college": [67, 1, 2], "parking": [49, 1, 114], "fuel": [66, -2, 19], "place_of_worship": [43, 0, 53], "post_office": [22, -2, 9], "university": [41, -1, 5]}, "maxspeed": {"*": [61, 0, 97]}, "sac_scale": {"*": [158, -4, 17]}, "surface": {"*": [105, 2, 131]}, "height": {"*": [73, 0, 3]}, "waterway": {"*": [174, 33, 17]}, "addr:housenumber": {"*": [89, -1, 21]}, "note": {"*": [46, 1, 41]}, "hgv": {"*": [43, -3, 8]}, "opening_hours": {"*": [197, 0, 1]}, "mtb:scale:*": {"*": [67, 11, 45]}, "ele": {"*": [89, -2, 34]}, "lit": {"*": [57, -4, 10]}, "width": {"*": [68, 2, 32]}, "boundary": {"*": [374, -1, 3]}, "type": {"restriction": [75, -4, 4]}, "highway": {"streets|road;service;pedestrian;living_street;residential;unclassified;tertiary;secondary_link;secondary;primary_link;primary;trunk_link;trunk;motorway_link;motorway;bus_guideway": [102, 1, 1921], "speed_camera": [43, 1, 1], "footway": [149, -1, 47], "motorway_junction": [59, 0, 10], "cycleway": [235, -2, 5], "bus_stop": [66, 8, 32], "steps": [85, -3, 21], "path": [191, -3, 32]}, "est_width": {"*": [27, -1, 1]}, "barrier": {"*": [104, -2, 44]}, "leisure": {"park": [128, -6, 8], "playground": [57, 0, 8], "pitch": [107, -2, 12]}, "historic": {"*": [79, 2, 16]}, "tourism": {"*": [60, 1, 44]}, "building": {"yes": [271, -2, 93], "*": [265, -2, 102], "church": [38, -2, 1]}, "traffic_calming": {"*": [19, 0, 5]}, "natural": {"tree": [108, -2, 1]}, "tunnel": {"*": [34, -1, 101]}, "wheelchair": {"*": [18, -1, 11]}, "aeroway": {"*": [123, 1, 2]}, "place": {"town": [25, 0, 7], "locality": [170, -2, 2], "*": [77, -1, 74], "hamlet": [56, -3, 46], "suburb": [107, 0, 2], "village": [89, 6, 16]}, "railway": {"*": [40, -1, 193]}, "landuse": {"residential": [239, -5, 4], "*": [262, -3, 22], "meadow": [124, 0, 2]}, "tracktype": {"*": [205, 13, 39]}, "route": {"mtb": [20, -1, 1], "bus": [47, 17, 2], "bicycle": [38, 0, 1], "road": [129, 3, 1], "hiking": [90, -20, 3]}}]