[{"Ways": [612, -1, 167], "Nodes": [1143, -5, 688], "Relations": [507, 3, 1]}, {"bridge": {"*": [422, 0, 6]}, "amenity": {"fast_food": [151, 0, 1], "place_of_worship": [372, -2, 4], "restaurant": [325, -1, 4], "bench": [189, -4, 1], "parking": [718, -4, 3]}, "maxspeed": {"*": [275, 0, 7]}, "power": {"generator": [52, 0, 1]}, "tracktype": {"*": [460, -36, 7]}, "tunnel": {"*": [680, -5, 1]}, "sac_scale": {"*": [58, 1, 47]}, "wheelchair": {"*": [96, 3, 2]}, "surface": {"*": [301, -14, 26]}, "ele": {"*": [389, -1, 2]}, "historic": {"*": [370, 0, 2]}, "place": {"*": [1003, -5, 1], "hamlet": [420, 0, 1]}, "waterway": {"*": [532, 6, 1]}, "tourism": {"*": [198, -1, 12]}, "highway": {"crossing": [222, 0, 1], "steps": [252, -2, 4], "streets|road;service;pedestrian;living_street;residential;unclassified;tertiary;secondary_link;secondary;primary_link;primary;trunk_link;trunk;motorway_link;motorway;bus_guideway": [770, -17, 59], "footway": [137, -1, 42], "path": [196, 0, 25]}}]