[{"Ways": [2799, -24, 9], "Nodes": [2200, -13, 295], "Relations": [660, -8, 1]}, {"bridge": {"*": [1152, -6, 1]}, "amenity": {"restaurant": [1141, -13, 1]}, "route": {"hiking": [194, 0, 1]}, "surface": {"*": [1233, -7, 3]}, "width": {"*": [525, -3, 2]}, "landuse": {"*": [1256, -11, 1], "forest": [412, 5, 1]}, "tracktype": {"*": [1249, -9, 1]}, "highway": {"streets|road;service;pedestrian;living_street;residential;unclassified;tertiary;secondary_link;secondary;primary_link;primary;trunk_link;trunk;motorway_link;motorway;bus_guideway": [4041, -28, 1], "footway": [1281, 3, 1]}}]