[{"Ways": [1511, -12, 41], "Nodes": [1266, -11, 910]}, {"bridge": {"*": [1301, -11, 1]}, "amenity": {"fuel": [355, -3, 3], "place_of_worship": [1108, -15, 1], "restaurant": [285, -2, 6], "bar": [572, -6, 1], "parking": [1198, -9, 2]}, "tunnel": {"*": [472, -4, 3]}, "surface": {"*": [1110, -7, 3]}, "note": {"*": [551, -10, 1]}, "historic": {"*": [795, -4, 1]}, "place": {"*": [632, -6, 3], "village": [399, -3, 3]}, "tourism": {"*": [1616, -17, 1]}, "highway": {"steps": [492, -5, 2], "streets|road;service;pedestrian;living_street;residential;unclassified;tertiary;secondary_link;secondary;primary_link;primary;trunk_link;trunk;motorway_link;motorway;bus_guideway": [1154, 6, 37]}}]