[{"Ways": [1154, -6, 88], "Nodes": [585, -3, 4542], "Relations": [564, -4, 2]}, {"building": {"yes": [1362, -15, 1], "*": [1385, -17, 1]}, "bridge": {"*": [1164, -2, 1]}, "sac_scale": {"*": [670, -14, 2]}, "route": {"road": [153, -4, 1]}, "note": {"*": [273, 0, 4]}, "waterway": {"*": [615, -11, 2]}, "landuse": {"*": [914, -6, 2]}, "boundary": {"*": [169, 3, 8]}, "highway": {"path": [587, -11, 10], "streets|road;service;pedestrian;living_street;residential;unclassified;tertiary;secondary_link;secondary;primary_link;primary;trunk_link;trunk;motorway_link;motorway;bus_guideway": [1062, -8, 49], "footway": [1275, -9, 1]}}]