[{"Ways": [178, 1, 1636], "Nodes": [101, -3, 36703], "Relations": [225, -5, 6]}, {"shop": {"*": [155, 16, 13]}, "bridge": {"*": [168, 0, 36]}, "amenity": {"drinking_water": [225, 0, 3], "place_of_worship": [194, -3, 10], "school": [610, -242, 1], "bar": [203, 134, 2], "restaurant": [283, -3, 5], "shelter": [145, 0, 1], "hospital": [73, -1, 3], "pharmacy": [181, -3, 3], "parking": [261, -1, 19], "fuel": [273, -4, 3], "post_office": [352, -4, 1], "bank": [210, -1, 2]}, "maxspeed": {"*": [186, 3, 16]}, "sac_scale": {"*": [117, -1, 21]}, "surface": {"*": [220, 6, 50]}, "waterway": {"*": [31, 0, 153]}, "addr:housenumber": {"*": [89, 14, 17]}, "opening_hours": {"*": [236, -1, 1]}, "mtb:scale:*": {"*": [66, -2, 41]}, "ele": {"*": [107, -3, 18]}, "width": {"*": [116, -2, 14]}, "boundary": {"*": [26, 1, 85]}, "highway": {"stop": [60, 0, 2], "path": [149, 4, 37], "streets|road;service;pedestrian;living_street;residential;unclassified;tertiary;secondary_link;secondary;primary_link;primary;trunk_link;trunk;motorway_link;motorway;bus_guideway": [183, -1, 836], "footway": [464, 0, 7], "steps": [129, -4, 11]}, "est_width": {"*": [30, 0, 1]}, "barrier": {"*": [242, 13, 8]}, "leisure": {"park": [171, -3, 5], "pitch": [94, -1, 12]}, "historic": {"*": [281, -3, 3]}, "tourism": {"*": [531, 5, 4]}, "building": {"yes": [173, 9, 154], "*": [175, 10, 155]}, "tunnel": {"*": [216, -3, 10]}, "wheelchair": {"*": [30, -5, 7]}, "place": {"hamlet": [102, -2, 17], "*": [83, -1, 56], "village": [241, -3, 4], "locality": [20, -1, 35]}, "railway": {"*": [70, 3, 63]}, "landuse": {"residential": [59, -1, 35], "*": [129, -2, 69], "meadow": [181, -5, 1]}, "tracktype": {"*": [120, -2, 72]}}]