[{"Ways": [1744, 0, 34], "Nodes": [1089, 0, 1437], "Relations": [896, 0, 1]}, {"barrier": {"*": [1007, 0, 1]}, "route": {"mtb": [35, 0, 1]}, "mtb:scale:*": {"*": [299, 0, 5]}, "landuse": {"*": [986, 0, 2], "forest": [308, 0, 2]}, "tracktype": {"*": [603, 0, 7]}, "highway": {"steps": [525, 0, 2], "streets|road;service;pedestrian;living_street;residential;unclassified;tertiary;secondary_link;secondary;primary_link;primary;trunk_link;trunk;motorway_link;motorway;bus_guideway": [2034, 0, 10], "path": [638, 0, 9]}}]