[{"Ways": [541, -27, 259], "Nodes": [540, -62, 3823]}, {"building": {"yes": [961, -15, 1], "*": [942, -17, 1]}, "amenity": {"drinking_water": [450, -3, 1], "place_of_worship": [306, 35, 6], "school": [190, 44, 5], "post_box": [228, -2, 1], "pharmacy": [147, -1, 4], "college": [37, -12, 3], "parking": [892, -7, 3], "post_office": [399, -5, 1], "bank": [185, 67, 3]}, "leisure": {"park": [497, -2, 1]}, "place": {"town": [246, -1, 1], "*": [1067, -5, 1]}, "surface": {"*": [1388, -15, 1]}, "boundary": {"*": [698, 3, 1]}, "landuse": {"*": [927, -4, 1]}, "tourism": {"*": [1630, -19, 1]}, "highway": {"steps": [238, -4, 5], "streets|road;service;pedestrian;living_street;residential;unclassified;tertiary;secondary_link;secondary;primary_link;primary;trunk_link;trunk;motorway_link;motorway;bus_guideway": [403, -22, 225]}}]