[{"Ways": [905, 87, 141], "Nodes": [1160, 209, 1187], "Relations": [613, -11, 1]}, {"shop": {"*": [1298, -10, 1]}, "building": {"yes": [388, 19, 74], "*": [395, 15, 74]}, "amenity": {"school": [946, -7, 1], "bench": [248, -3, 1], "pub": [339, 0, 1], "parking": [1371, 625, 2]}, "tracktype": {"*": [432, 34, 14]}, "sac_scale": {"*": [195, 15, 17]}, "route": {"bus": [93, 3, 1]}, "mtb:scale:*": {"*": [585, -133, 1]}, "surface": {"*": [1897, -5, 1]}, "ele": {"*": [245, 31, 7]}, "landuse": {"residential": [389, -3, 2], "*": [726, 96, 4], "forest": [429, 0, 1]}, "tourism": {"*": [465, -2, 7]}, "highway": {"bus_stop": [803, -7, 1], "streets|road;service;pedestrian;living_street;residential;unclassified;tertiary;secondary_link;secondary;primary_link;primary;trunk_link;trunk;motorway_link;motorway;bus_guideway": [1456, 219, 23], "path": [494, 22, 13]}}]