[{"Ways": [341, -3, 715], "Nodes": [334, -1, 9680], "Relations": [545, -2, 1]}, {"shop": {"*": [293, 0, 7]}, "bridge": {"*": [326, -1, 14]}, "amenity": {"drinking_water": [131, 0, 10], "restaurant": [201, -1, 8], "bar": [386, -10, 1], "parking": [440, -7, 10]}, "note": {"*": [413, -2, 1]}, "building": {"yes": [557, -17, 12], "*": [519, -18, 17]}, "barrier": {"*": [639, -5, 1]}, "tracktype": {"*": [270, -3, 26]}, "sac_scale": {"*": [375, -3, 4]}, "mtb:scale:*": {"*": [129, -1, 16]}, "surface": {"*": [310, 5, 36]}, "ele": {"*": [291, -6, 4]}, "lit": {"*": [178, -4, 1]}, "historic": {"*": [232, 29, 5]}, "place": {"hamlet": [127, -1, 16], "*": [174, 1, 25], "village": [158, 0, 8], "locality": [243, -1, 1]}, "leisure": {"park": [157, 1, 6], "pitch": [421, -4, 1]}, "railway": {"*": [349, -28, 4]}, "waterway": {"*": [317, -2, 5]}, "landuse": {"*": [547, -5, 5]}, "tourism": {"*": [1514, -20, 1]}, "boundary": {"*": [189, 24, 6]}, "highway": {"path": [650, -55, 5], "streets|road;service;pedestrian;living_street;residential;unclassified;tertiary;secondary_link;secondary;primary_link;primary;trunk_link;trunk;motorway_link;motorway;bus_guideway": [359, 2, 311], "footway": [676, -12, 4], "cycleway": [19, -2, 93]}}]