[{"Ways": [683, -7, 185], "Nodes": [985, -2, 1204], "Relations": [225, -2, 8]}, {"shop": {"*": [492, -9, 3]}, "bridge": {"*": [337, 17, 12]}, "amenity": {"fuel": [371, -3, 2], "place_of_worship": [936, -10, 1], "cafe": [463, -7, 1], "college": [93, 0, 1], "parking": [1093, -4, 2]}, "building": {"yes": [305, -4, 73], "*": [308, -4, 73]}, "barrier": {"*": [427, -6, 3]}, "tunnel": {"*": [358, 2, 4]}, "highway": {"steps": [525, -5, 1], "streets|road;service;pedestrian;living_street;residential;unclassified;tertiary;secondary_link;secondary;primary_link;primary;trunk_link;trunk;motorway_link;motorway;bus_guideway": [784, 6, 70], "motorway_junction": [103, 0, 3], "footway": [360, -4, 13], "cycleway": [94, -3, 18]}}]