[{"Ways": [1366, -7, 33], "Nodes": [1397, -4, 487]}, {"shop": {"*": [1241, -6, 1]}, "amenity": {"post_box": [99, 0, 2], "telephone": [259, -1, 1], "parking": [567, -2, 6]}, "barrier": {"*": [438, -6, 3]}, "surface": {"*": [814, 20, 4]}, "historic": {"*": [266, -4, 4]}, "place": {"*": [752, -2, 2], "village": [489, 1, 2]}, "landuse": {"residential": [494, -6, 1], "*": [1109, -20, 1]}, "tourism": {"*": [1486, -1, 1]}, "highway": {"streets|road;service;pedestrian;living_street;residential;unclassified;tertiary;secondary_link;secondary;primary_link;primary;trunk_link;trunk;motorway_link;motorway;bus_guideway": [1141, -4, 25]}}]