[{"Ways": [1086, -6, 104], "Nodes": [806, -6, 2794], "Relations": [927, -17, 1]}, {"shop": {"*": [361, 45, 7]}, "bridge": {"*": [996, -10, 2]}, "amenity": {"fast_food": [349, -3, 1], "bar": [390, -6, 2], "pharmacy": [386, -2, 2], "parking": [833, -5, 5], "fuel": [321, -4, 4], "bank": [351, -3, 2]}, "maxspeed": {"*": [585, -7, 3]}, "building": {"yes": [1094, -14, 3], "*": [1112, -17, 3]}, "barrier": {"*": [1028, -6, 1]}, "tracktype": {"*": [936, -11, 3]}, "surface": {"*": [2037, -27, 1]}, "ele": {"*": [862, -3, 1]}, "width": {"*": [808, 1, 1]}, "place": {"village": [559, -1, 2], "*": [441, 3, 7], "hamlet": [294, -1, 5]}, "leisure": {"park": [708, -5, 1]}, "railway": {"*": [721, -4, 1]}, "landuse": {"*": [569, -13, 8]}, "tourism": {"*": [846, -9, 3]}, "highway": {"bus_stop": [238, -2, 7], "streets|road;service;pedestrian;living_street;residential;unclassified;tertiary;secondary_link;secondary;primary_link;primary;trunk_link;trunk;motorway_link;motorway;bus_guideway": [1035, -18, 55], "motorway_junction": [126, -2, 2], "footway": [589, 0, 7]}}]