[{"Ways": [141, -3, 3455], "Nodes": [90, -4, 57973], "Relations": [451, -10, 3]}, {"shop": {"*": [24, -2, 111]}, "bridge": {"*": [115, -2, 78]}, "amenity": {"fast_food": [319, -6, 1], "drinking_water": [145, 4, 12], "school": [200, -1, 6], "bar": [11, 0, 43], "clock": [24, 0, 1], "restaurant": [54, -4, 29], "pub": [35, -1, 7], "pharmacy": [52, 4, 10], "college": [27, 2, 4], "parking": [151, -6, 45], "fuel": [170, -4, 8], "place_of_worship": [142, 6, 19], "post_office": [94, -2, 4], "cafe": [356, 339, 2], "bank": [28, 0, 17]}, "maxspeed": {"*": [273, -9, 12]}, "building": {"yes": [384, -18, 72], "*": [377, -13, 79]}, "tunnel": {"*": [145, -2, 24]}, "opening_hours": {"*": [159, 4, 1]}, "landuse": {"*": [485, 11, 10], "meadow": [200, -7, 1]}, "surface": {"*": [1079, -31, 4]}, "height": {"*": [17, -2, 63]}, "railway": {"*": [40, 1, 208]}, "historic": {"*": [546, -13, 2]}, "place": {"town": [315, -2, 1], "*": [132, 1, 41], "village": [33, 0, 38], "hamlet": [452, -14, 2]}, "leisure": {"park": [264, -1, 4], "playground": [298, -11, 2], "pitch": [612, -20, 1]}, "addr:housenumber": {"*": [131, -5, 17]}, "tourism": {"*": [452, -11, 7]}, "waterway": {"*": [612, -13, 2]}, "ele": {"*": [2, 0, 29748]}, "type": {"restriction": [134, -2, 1]}, "boundary": {"*": [509, 395, 2]}, "highway": {"streets|road;service;pedestrian;living_street;residential;unclassified;tertiary;secondary_link;secondary;primary_link;primary;trunk_link;trunk;motorway_link;motorway;bus_guideway": [69, -3, 2959], "footway": [231, -8, 31], "motorway_junction": [19, 0, 36], "cycleway": [258, -2, 5], "steps": [399, -2, 3], "crossing": [134, -3, 6], "path": [1161, -45, 2]}}]