[{"Ways": [3369, -23, 5], "Nodes": [2360, -28, 252]}, {"shop": {"*": [1083, -14, 1]}, "amenity": {"school": [938, -11, 1], "restaurant": [496, 0, 3], "pub": [136, 0, 2], "pharmacy": [319, 2, 2], "parking": [1184, -4, 2], "cafe": [611, -2, 1]}, "tourism": {"*": [1004, 0, 2]}, "highway": {"streets|road;service;pedestrian;living_street;residential;unclassified;tertiary;secondary_link;secondary;primary_link;primary;trunk_link;trunk;motorway_link;motorway;bus_guideway": [3006, -12, 3], "footway": [952, -1, 2]}, "surface": {"*": [1648, 0, 1]}}]