[{"Ways": [1297, -9, 45], "Nodes": [2700, -17, 80], "Relations": [136, -3, 22]}, {"amenity": {"restaurant": [1037, -8, 1], "parking": [1067, -5, 2]}, "ele": {"*": [135, 4, 15]}, "note": {"*": [90, -15, 18]}, "place": {"*": [453, -8, 5], "locality": [92, -2, 5]}, "boundary": {"*": [38, 0, 43]}, "landuse": {"*": [989, 0, 1], "forest": [347, 0, 1]}, "highway": {"streets|road;service;pedestrian;living_street;residential;unclassified;tertiary;secondary_link;secondary;primary_link;primary;trunk_link;trunk;motorway_link;motorway;bus_guideway": [2367, -11, 4]}}]