[{"Ways": [1013, -8, 91], "Nodes": [910, -3, 1564]}, {"shop": {"*": [1219, -10, 1]}, "amenity": {"bench": [188, -4, 1]}, "maxspeed": {"*": [378, -3, 5]}, "mtb:scale:*": {"*": [356, -60, 2]}, "surface": {"*": [618, -25, 10]}, "lit": {"*": [145, -4, 1]}, "width": {"*": [596, -12, 1]}, "place": {"*": [759, -15, 2], "village": [451, -2, 2]}, "leisure": {"playground": [475, -10, 1]}, "waterway": {"*": [509, -2, 2]}, "landuse": {"residential": [335, -7, 2], "*": [466, -28, 8], "forest": [229, -45, 2]}, "tracktype": {"*": [417, -5, 12]}, "boundary": {"*": [338, 109, 3]}, "highway": {"path": [548, -3, 8], "streets|road;service;pedestrian;living_street;residential;unclassified;tertiary;secondary_link;secondary;primary_link;primary;trunk_link;trunk;motorway_link;motorway;bus_guideway": [1303, -44, 24], "cycleway": [262, -1, 4]}}]