[{"Ways": [792, -4, 142], "Nodes": [113, -1, 40358]}, {"shop": {"*": [471, 0, 3]}, "bridge": {"*": [503, -4, 5]}, "amenity": {"fast_food": [203, -3, 1], "post_office": [554, -5, 1], "pub": [220, -2, 1], "restaurant": [594, -4, 2]}, "tunnel": {"*": [805, -8, 1]}, "tracktype": {"*": [606, -4, 5]}, "place": {"town": [311, -1, 1], "*": [151, -2, 32], "village": [43, 0, 31]}, "tourism": {"*": [96, 2, 31]}, "highway": {"streets|road;service;pedestrian;living_street;residential;unclassified;tertiary;secondary_link;secondary;primary_link;primary;trunk_link;trunk;motorway_link;motorway;bus_guideway": [601, -5, 121], "footway": [585, 12, 5]}}]