[{"Ways": [184, 0, 2897], "Nodes": [232, -1, 21265], "Relations": [276, 2, 9]}, {"building": {"yes": [368, -9, 110], "*": [375, -11, 110]}, "bridge": {"*": [315, -5, 20]}, "amenity": {"fuel": [366, -4, 3], "parking": [1904, -8, 1]}, "maxspeed": {"*": [282, -3, 12]}, "tracktype": {"*": [1341, -8, 1]}, "surface": {"*": [1040, -13, 5]}, "aeroway": {"*": [75, -2, 4]}, "place": {"town": [239, 2, 1], "*": [684, -3, 3], "village": [502, 1, 2]}, "leisure": {"pitch": [364, -6, 3]}, "railway": {"*": [620, 8, 1]}, "waterway": {"*": [436, 50, 4]}, "landuse": {"residential": [230, 0, 7], "*": [606, -12, 7]}, "tourism": {"*": [2093, -18, 1]}, "boundary": {"*": [484, 12, 2]}, "highway": {"steps": [735, -6, 1], "streets|road;service;pedestrian;living_street;residential;unclassified;tertiary;secondary_link;secondary;primary_link;primary;trunk_link;trunk;motorway_link;motorway;bus_guideway": [87, -1, 2674]}}]