[{"Ways": [268, -6, 1604], "Nodes": [152, -1, 40490], "Relations": [391, 1, 4]}, {"shop": {"*": [1220, -17, 1]}, "bridge": {"*": [336, 2, 18]}, "amenity": {"drinking_water": [612, -2, 1], "place_of_worship": [133, 2, 22], "school": [291, 1, 4], "restaurant": [301, 2, 6], "hospital": [285, -4, 1], "telephone": [161, -2, 1], "pub": [243, -1, 1], "pharmacy": [578, -4, 1], "parking": [326, -9, 19], "fuel": [213, -2, 6], "post_office": [427, -3, 1], "cafe": [297, 204, 2]}, "maxspeed": {"*": [134, 1, 45]}, "building": {"yes": [614, -1, 22], "*": [623, -2, 22]}, "barrier": {"*": [429, -5, 5]}, "hgv": {"*": [42, -1, 11]}, "tracktype": {"*": [185, -5, 64]}, "landuse": {"residential": [77, 0, 42], "*": [155, -5, 103]}, "surface": {"*": [163, 3, 115]}, "ele": {"*": [362, 19, 4]}, "tunnel": {"*": [298, 29, 8]}, "historic": {"*": [117, -2, 14]}, "place": {"town": [175, 0, 1], "suburb": [134, 0, 1], "*": [80, -1, 89], "village": [105, 1, 14], "hamlet": [52, -2, 73]}, "leisure": {"park": [228, -30, 5], "playground": [434, -1, 1], "pitch": [293, -3, 4]}, "addr:housenumber": {"*": [92, 2, 39]}, "waterway": {"*": [245, -11, 14], "river": [224, -63, 1]}, "aeroway": {"*": [119, -1, 2]}, "tourism": {"*": [486, -6, 7]}, "boundary": {"*": [203, -6, 6]}, "highway": {"steps": [243, -4, 7], "streets|road;service;pedestrian;living_street;residential;unclassified;tertiary;secondary_link;secondary;primary_link;primary;trunk_link;trunk;motorway_link;motorway;bus_guideway": [165, 0, 1284], "motorway_junction": [39, 0, 17], "footway": [353, -2, 16]}}]