[{"Ways": [616, 23, 325], "Nodes": [1191, 42, 1202]}, {"shop": {"*": [1608, -2, 1]}, "bridge": {"*": [674, -3, 4]}, "amenity": {"drinking_water": [267, -4, 5], "place_of_worship": [889, -1, 2], "school": [965, 1, 1], "bar": [636, -3, 1], "telephone": [248, 12, 1], "pharmacy": [351, -2, 2], "parking": [221, 10, 30], "post_office": [585, -3, 1], "cafe": [350, 3, 2]}, "surface": {"*": [551, 5, 18]}, "place": {"suburb": [83, 0, 3], "*": [606, -1, 4], "village": [871, 5, 1]}, "leisure": {"playground": [299, 3, 2], "pitch": [165, 1, 9]}, "boundary": {"*": [301, 3, 4]}, "landuse": {"*": [1025, 5, 2]}, "tracktype": {"*": [537, -2, 10]}, "highway": {"bus_stop": [135, 0, 17], "streets|road;service;pedestrian;living_street;residential;unclassified;tertiary;secondary_link;secondary;primary_link;primary;trunk_link;trunk;motorway_link;motorway;bus_guideway": [442, 30, 256], "footway": [294, -4, 22], "cycleway": [174, 2, 9]}}]