[{"Ways": [1815, -11, 29], "Nodes": [2370, -14, 213], "Relations": [398, 2, 4]}, {"tracktype": {"*": [722, 8, 4]}, "sac_scale": {"*": [562, -5, 3]}, "route": {"hiking": [77, -2, 4]}, "surface": {"*": [1033, -3, 4]}, "ele": {"*": [784, -4, 1]}, "historic": {"*": [936, -4, 1]}, "tourism": {"*": [670, 126, 4]}, "highway": {"steps": [784, -8, 1], "streets|road;service;pedestrian;living_street;residential;unclassified;tertiary;secondary_link;secondary;primary_link;primary;trunk_link;trunk;motorway_link;motorway;bus_guideway": [3732, -29, 1], "footway": [1174, -3, 1], "path": [440, 16, 15]}}]