[{"Ways": [385, -2, 780], "Nodes": [340, -1, 11989]}, {"shop": {"*": [1203, -12, 1]}, "bridge": {"*": [220, -5, 32]}, "amenity": {"drinking_water": [13, 0, 102], "place_of_worship": [363, -3, 6], "school": [361, -2, 3], "restaurant": [1086, -7, 1], "parking": [1228, -1, 2]}, "maxspeed": {"*": [683, -1, 2]}, "natural": {"tree": [117, -1, 1]}, "barrier": {"*": [502, 1, 4]}, "tunnel": {"*": [188, -4, 17]}, "mtb:scale:*": {"*": [375, -6, 3]}, "surface": {"*": [903, -8, 6]}, "note": {"*": [258, -24, 4]}, "historic": {"*": [722, -1, 1]}, "place": {"town": [173, 1, 1], "*": [379, -2, 8], "village": [901, -5, 1], "hamlet": [290, -1, 5]}, "leisure": {"park": [667, -5, 1]}, "railway": {"*": [109, -1, 42]}, "waterway": {"*": [182, 0, 25], "river": [203, 4, 2]}, "tracktype": {"*": [851, 1, 3]}, "boundary": {"*": [448, -102, 2]}, "highway": {"steps": [183, -3, 11], "path": [439, -19, 17], "streets|road;service;pedestrian;living_street;residential;unclassified;tertiary;secondary_link;secondary;primary_link;primary;trunk_link;trunk;motorway_link;motorway;bus_guideway": [293, -4, 546], "footway": [482, -5, 10], "cycleway": [609, 0, 1]}}]