[{"Ways": [763, -12, 133], "Nodes": [1303, -10, 620], "Relations": [575, -9, 1]}, {"bridge": {"*": [449, 1, 6]}, "amenity": {"fast_food": [184, -5, 1], "place_of_worship": [412, -2, 4], "restaurant": [366, 0, 4], "bench": [216, -2, 1], "parking": [976, -5, 2]}, "maxspeed": {"*": [351, -3, 5]}, "power": {"generator": [91, -2, 1]}, "tracktype": {"*": [541, 37, 6]}, "tunnel": {"*": [731, -4, 1]}, "sac_scale": {"*": [79, 7, 39]}, "wheelchair": {"*": [128, -3, 2]}, "surface": {"*": [366, 14, 23]}, "ele": {"*": [438, -5, 2]}, "historic": {"*": [692, -4, 1]}, "place": {"*": [1089, -9, 1], "hamlet": [468, 0, 1]}, "landuse": {"*": [573, -11, 4], "forest": [319, -6, 1]}, "tourism": {"*": [234, 0, 11]}, "highway": {"crossing": [257, -2, 1], "steps": [284, -1, 4], "streets|road;service;pedestrian;living_street;residential;unclassified;tertiary;secondary_link;secondary;primary_link;primary;trunk_link;trunk;motorway_link;motorway;bus_guideway": [943, -6, 42], "footway": [177, -5, 37], "path": [262, 32, 21]}}]