[{"Ways": [284, -1, 719], "Nodes": [1348, -2, 470], "Relations": [475, -3, 1]}, {"addr:housenumber": {"*": [183, -2, 3]}, "bridge": {"*": [210, 0, 24]}, "amenity": {"fuel": [492, 1, 1], "place_of_worship": [805, -2, 1], "restaurant": [935, -6, 1], "cafe": [387, -3, 1], "parking": [594, -4, 5]}, "maxspeed": {"*": [266, 28, 7]}, "building": {"yes": [770, -9, 1], "*": [784, -7, 1]}, "barrier": {"*": [469, -5, 2]}, "tracktype": {"*": [194, 4, 34]}, "hgv": {"*": [76, 0, 2]}, "sac_scale": {"*": [169, 19, 13]}, "wheelchair": {"*": [65, -17, 3]}, "landuse": {"residential": [167, 2, 5], "*": [376, -3, 8], "forest": [176, 6, 1]}, "mtb:scale:*": {"*": [110, 12, 15]}, "surface": {"*": [177, 2, 61]}, "note": {"*": [457, -5, 1]}, "width": {"*": [87, 1, 18]}, "railway": {"*": [274, -30, 6]}, "waterway": {"*": [394, -2, 2]}, "tunnel": {"*": [272, -3, 6]}, "tourism": {"*": [429, 3, 5]}, "boundary": {"*": [585, 5, 1]}, "highway": {"streets|road;service;pedestrian;living_street;residential;unclassified;tertiary;secondary_link;secondary;primary_link;primary;trunk_link;trunk;motorway_link;motorway;bus_guideway": [235, 1, 555], "footway": [230, -4, 21], "motorway_junction": [123, -3, 1], "cycleway": [201, -2, 5], "steps": [212, -2, 5], "path": [143, 11, 37]}}]