[{"Ways": [1371, -62, 35], "Nodes": [2323, -18, 120]}, {"shop": {"*": [372, -55, 4]}, "amenity": {"place_of_worship": [588, -7, 2], "school": [357, 2, 2], "bar": [306, -7, 1], "university": [96, -2, 1], "parking": [532, -4, 7], "post_office": [237, 0, 1]}, "leisure": {"park": [293, -4, 2], "pitch": [277, -3, 2]}, "landuse": {"*": [536, -5, 4]}, "tourism": {"*": [708, 0, 3]}, "highway": {"streets|road;service;pedestrian;living_street;residential;unclassified;tertiary;secondary_link;secondary;primary_link;primary;trunk_link;trunk;motorway_link;motorway;bus_guideway": [1292, -40, 19], "cycleway": [390, -3, 1]}}]