[{"Ways": [438, -2, 457], "Nodes": [697, -2, 2651]}, {"shop": {"*": [291, 0, 7]}, "building": {"yes": [853, -11, 2], "*": [865, -13, 2]}, "amenity": {"place_of_worship": [465, -4, 3], "school": [162, 2, 6], "bar": [77, 0, 7], "restaurant": [423, -3, 3], "hospital": [210, -5, 1], "telephone": [186, -1, 1], "pub": [95, -3, 2], "pharmacy": [420, -2, 1], "parking": [358, -6, 13], "fuel": [356, -2, 2], "post_office": [482, -4, 1], "bank": [170, 0, 3]}, "tracktype": {"*": [799, -6, 2]}, "surface": {"*": [1164, -8, 2]}, "ele": {"*": [279, -6, 5]}, "note": {"*": [308, -1, 2]}, "historic": {"*": [199, -4, 6]}, "place": {"town": [258, 0, 1], "*": [661, -5, 2], "village": [569, -2, 1]}, "leisure": {"park": [184, -4, 5], "pitch": [255, -3, 3]}, "railway": {"*": [279, 0, 7]}, "waterway": {"*": [589, 0, 1]}, "landuse": {"residential": [67, -2, 40], "*": [203, 1, 45]}, "tourism": {"*": [1501, -20, 1]}, "boundary": {"*": [387, 167, 2]}, "highway": {"crossing": [264, -2, 1], "path": [1071, -18, 1], "streets|road;service;pedestrian;living_street;residential;unclassified;tertiary;secondary_link;secondary;primary_link;primary;trunk_link;trunk;motorway_link;motorway;bus_guideway": [392, 0, 263], "footway": [641, -9, 4]}}]