[{"Ways": [1728, -15, 21], "Nodes": [955, -3, 1296]}, {"shop": {"*": [954, -13, 1]}, "bridge": {"*": [634, -3, 3]}, "amenity": {"place_of_worship": [927, -10, 1], "restaurant": [582, 0, 2], "pharmacy": [401, -5, 1], "parking": [948, -2, 2]}, "barrier": {"*": [549, -9, 2]}, "tracktype": {"*": [1022, -227, 1]}, "tunnel": {"*": [570, 1, 1]}, "sac_scale": {"*": [689, 2, 1]}, "surface": {"*": [760, -53, 5]}, "ele": {"*": [565, 1, 1]}, "landuse": {"*": [540, -1, 5], "forest": [165, -2, 3]}, "tourism": {"*": [792, -7, 2]}, "highway": {"path": [786, 9, 3], "streets|road;service;pedestrian;living_street;residential;unclassified;tertiary;secondary_link;secondary;primary_link;primary;trunk_link;trunk;motorway_link;motorway;bus_guideway": [1855, -11, 8]}}]