[{"Ways": [659, -6, 187], "Nodes": [2765, -21, 62], "Relations": [163, -2, 14]}, {"building": {"yes": [1094, -12, 1], "*": [1113, -14, 1]}, "amenity": {"post_box": [305, -3, 1], "restaurant": [1164, -10, 1]}, "barrier": {"*": [162, 0, 20]}, "hgv": {"*": [133, 0, 1]}, "width": {"*": [623, -1, 1]}, "highway": {"steps": [190, 1, 8], "streets|road;service;pedestrian;living_street;residential;unclassified;tertiary;secondary_link;secondary;primary_link;primary;trunk_link;trunk;motorway_link;motorway;bus_guideway": [473, 2, 171], "footway": [592, -3, 5]}}]