[{"Ways": [525, -7, 454], "Nodes": [702, -5, 3659]}, {"building": {"yes": [255, -4, 228], "*": [259, -3, 228]}, "amenity": {"restaurant": [894, -11, 1]}, "maxspeed": {"*": [219, -4, 17]}, "barrier": {"*": [356, -3, 7]}, "surface": {"*": [374, -5, 36]}, "note": {"*": [40, 4, 47]}, "leisure": {"playground": [356, 0, 1]}, "highway": {"path": [1121, -11, 2], "streets|road;service;pedestrian;living_street;residential;unclassified;tertiary;secondary_link;secondary;primary_link;primary;trunk_link;trunk;motorway_link;motorway;bus_guideway": [629, -3, 142], "footway": [240, -7, 29], "cycleway": [212, -1, 6]}}]