[{"Ways": [1158, -8, 51], "Nodes": [610, -4, 2977]}, {"addr:housenumber": {"*": [93, -1, 18]}, "building": {"yes": [485, -10, 12], "*": [492, -10, 12]}, "amenity": {"drinking_water": [306, -2, 2], "place_of_worship": [714, -4, 2], "restaurant": [425, -5, 3], "shelter": [72, -1, 2], "fuel": [586, -3, 1], "post_office": [76, -2, 4]}, "landuse": {"*": [930, -5, 1]}, "tracktype": {"*": [267, -2, 24]}, "hgv": {"*": [160, -1, 1]}, "sac_scale": {"*": [369, -44, 4]}, "surface": {"*": [366, -8, 24]}, "height": {"*": [35, -2, 12]}, "width": {"*": [71, -3, 28]}, "historic": {"*": [383, -3, 2]}, "place": {"village": [664, -2, 1], "*": [680, -8, 2], "locality": [229, 1, 1]}, "waterway": {"*": [607, -5, 1]}, "ele": {"*": [244, 0, 5]}, "tourism": {"*": [892, 1, 2]}, "highway": {"path": [765, -80, 3], "streets|road;service;pedestrian;living_street;residential;unclassified;tertiary;secondary_link;secondary;primary_link;primary;trunk_link;trunk;motorway_link;motorway;bus_guideway": [1861, 1, 7]}}]