[{"Ways": [2838, -21, 9], "Nodes": [5435, -34, 6], "Relations": [633, -2, 1]}, {"shop": {"*": [723, -12, 2]}, "addr:housenumber": {"*": [222, 0, 5]}, "amenity": {"fast_food": [174, -1, 1], "restaurant": [476, -2, 3]}, "building": {"yes": [1084, -6, 2], "*": [1101, -7, 2]}, "tunnel": {"*": [367, -3, 5]}, "tourism": {"*": [768, -2, 3]}, "highway": {"streets|road;service;pedestrian;living_street;residential;unclassified;tertiary;secondary_link;secondary;primary_link;primary;trunk_link;trunk;motorway_link;motorway;bus_guideway": [2260, -14, 7]}}]