[{"Ways": [1368, -5, 39], "Nodes": [719, -3, 2363]}, {"shop": {"*": [1091, -14, 1]}, "amenity": {"fast_food": [182, 1, 1], "drinking_water": [491, -8, 1], "restaurant": [467, -6, 3], "bar": [270, 0, 2], "parking": [1114, -9, 2]}, "maxspeed": {"*": [647, -7, 1]}, "tracktype": {"*": [548, -39, 6]}, "historic": {"*": [659, -6, 1]}, "tourism": {"*": [435, -1, 6]}, "highway": {"path": [1140, -6, 1], "streets|road;service;pedestrian;living_street;residential;unclassified;tertiary;secondary_link;secondary;primary_link;primary;trunk_link;trunk;motorway_link;motorway;bus_guideway": [1175, -5, 27], "footway": [1123, -18, 1]}}]