[{"Ways": [1464, -7, 22], "Nodes": [679, -1, 1939]}, {"amenity": {"place_of_worship": [693, -5, 1], "restaurant": [664, -7, 1], "parking": [838, -3, 2]}, "sac_scale": {"*": [240, -20, 7]}, "surface": {"*": [1271, 2, 1]}, "ele": {"*": [231, 0, 4]}, "place": {"hamlet": [354, -2, 1], "*": [342, -2, 6], "village": [224, 0, 4], "locality": [149, 4, 1]}, "boundary": {"*": [484, 0, 1]}, "tourism": {"*": [936, -9, 1]}, "highway": {"path": [459, -37, 7], "streets|road;service;pedestrian;living_street;residential;unclassified;tertiary;secondary_link;secondary;primary_link;primary;trunk_link;trunk;motorway_link;motorway;bus_guideway": [1543, 128, 9], "footway": [833, -1, 1]}}]