[{"Ways": [1343, 364, 35], "Nodes": [1873, 170, 230]}, {"maxspeed": {"*": [438, 0, 3]}, "leisure": {"pitch": [443, 0, 1]}, "place": {"town": [194, 0, 1], "*": [1199, 0, 1]}, "surface": {"*": [1262, 0, 1]}, "landuse": {"residential": [474, 0, 1], "*": [744, 297, 2]}, "highway": {"streets|road;service;pedestrian;living_street;residential;unclassified;tertiary;secondary_link;secondary;primary_link;primary;trunk_link;trunk;motorway_link;motorway;bus_guideway": [1142, 278, 26], "footway": [702, 0, 3]}}]