[{"Ways": [649, -10, 291], "Nodes": [586, -7, 4733], "Relations": [227, -1, 11]}, {"shop": {"*": [1411, -13, 1]}, "building": {"yes": [591, -16, 23], "*": [600, -18, 23]}, "amenity": {"place_of_worship": [808, -7, 2], "hospital": [349, 2, 1], "pub": [289, 0, 1], "pharmacy": [330, -3, 2], "parking": [408, -8, 13], "fuel": [748, -8, 1], "post_office": [506, -9, 1], "cafe": [580, -4, 1], "bank": [105, -2, 7]}, "tracktype": {"*": [526, -34, 10]}, "tunnel": {"*": [559, 5, 2]}, "sac_scale": {"*": [651, -4, 2]}, "mtb:scale:*": {"*": [86, -6, 47]}, "surface": {"*": [415, -10, 30]}, "height": {"*": [200, -3, 1]}, "width": {"*": [166, 15, 13]}, "historic": {"*": [528, -4, 2]}, "place": {"*": [787, -4, 2], "village": [492, 3, 2]}, "leisure": {"park": [430, -7, 2], "playground": [493, -9, 1], "pitch": [289, -7, 4]}, "landuse": {"residential": [534, 0, 1], "*": [151, 4, 102], "forest": [169, -5, 6]}, "tourism": {"*": [617, -9, 5]}, "highway": {"path": [206, -5, 45], "streets|road;service;pedestrian;living_street;residential;unclassified;tertiary;secondary_link;secondary;primary_link;primary;trunk_link;trunk;motorway_link;motorway;bus_guideway": [954, 7, 63], "footway": [875, -103, 3], "cycleway": [403, 4, 2]}}]