[{"Ways": [1870, -3, 26], "Nodes": [1580, 2, 589]}, {"shop": {"*": [782, -3, 2]}, "building": {"yes": [1312, 1, 1], "*": [1334, 1, 1]}, "amenity": {"drinking_water": [677, -3, 1], "place_of_worship": [1101, 0, 1], "restaurant": [1115, 0, 1], "cafe": [227, 2, 3], "parking": [1674, 7, 1]}, "tracktype": {"*": [1186, -139, 1]}, "surface": {"*": [1171, -6, 3]}, "place": {"*": [1165, 5, 1], "hamlet": [637, -2, 1]}, "landuse": {"*": [1198, 4, 1]}, "tourism": {"*": [1066, 1, 2]}, "highway": {"streets|road;service;pedestrian;living_street;residential;unclassified;tertiary;secondary_link;secondary;primary_link;primary;trunk_link;trunk;motorway_link;motorway;bus_guideway": [1549, 9, 19], "footway": [1258, -11, 1]}}]