[{"Ways": [1533, -20, 34], "Nodes": [2187, -27, 197]}, {"shop": {"*": [127, -1, 22]}, "building": {"yes": [822, -18, 3], "*": [737, -17, 5]}, "amenity": {"drinking_water": [539, -16, 1], "place_of_worship": [304, -1, 7], "school": [763, -5, 1], "cafe": [514, -2, 1], "bar": [154, -2, 4], "restaurant": [395, -3, 4], "hospital": [297, 2, 1], "pub": [112, 0, 2], "pharmacy": [577, -7, 1], "parking": [1166, -5, 2], "fuel": [658, -7, 1], "post_office": [182, 0, 2], "bench": [253, 0, 1]}, "leisure": {"playground": [367, -7, 1]}, "historic": {"*": [346, -2, 3]}, "surface": {"*": [942, -9, 4]}, "landuse": {"*": [692, -12, 3], "forest": [325, 3, 1]}, "tourism": {"*": [407, -8, 7]}, "highway": {"streets|road;service;pedestrian;living_street;residential;unclassified;tertiary;secondary_link;secondary;primary_link;primary;trunk_link;trunk;motorway_link;motorway;bus_guideway": [1342, -37, 23]}}]