[{"Ways": [4, 0, 45744], "Nodes": [2, 0, 1245225], "Relations": [5, 0, 1184]}, {"shop": {"*": [5, 0, 344]}, "bridge": {"*": [5, 0, 1193]}, "amenity": {"fast_food": [7, 0, 21], "drinking_water": [9, 0, 119], "waste_basket": [2, 0, 73], "bar": [141, -1, 4], "school": [33, -1, 19], "clock": [1, 0, 12], "shelter": [13, 0, 11], "place_of_worship": [41, 1, 54], "hospital": [120, -2, 2], "restaurant": [9, 0, 88], "telephone": [10, 0, 26], "pub": [50, -1, 4], "bench": [3, 0, 171], "post_box": [4, 0, 39], "parking": [11, 5, 227], "fuel": [12, 0, 51], "pharmacy": [39, -1, 11], "post_office": [28, 0, 8], "cafe": [4, 0, 101], "bank": [12, 0, 28]}, "maxspeed": {"*": [24, 0, 266]}, "office": {"*": [2, 0, 24]}, "sac_scale": {"*": [4, 0, 377]}, "surface": {"*": [2, 0, 2975]}, "height": {"*": [30, -1, 14]}, "waterway": {"*": [1, 0, 31502], "river": [1, 0, 1701]}, "addr:housenumber": {"*": [3, 0, 2729]}, "note": {"*": [4, 0, 1009]}, "parking:lane:*": {"no_parking": [4, -1, 5], "*": [9, -1, 12]}, "hgv": {"*": [3, 0, 121]}, "opening_hours": {"*": [2, 0, 158]}, "mtb:scale:*": {"*": [25, -2, 158]}, "ele": {"*": [6, 0, 3680]}, "lit": {"*": [2, 1, 1579]}, "width": {"*": [3, 0, 384]}, "boundary": {"*": [3, 0, 1543]}, "type": {"restriction": [11, 0, 48]}, "highway": {"streets|road;service;pedestrian;living_street;residential;unclassified;tertiary;secondary_link;secondary;primary_link;primary;trunk_link;trunk;motorway_link;motorway;bus_guideway": [30, -1, 5485], "speed_camera": [64, 0, 1], "footway": [23, 3, 258], "stop": [2, 0, 140], "motorway_junction": [17, 0, 37], "cycleway": [2, -1, 193], "bus_stop": [15, 0, 176], "steps": [27, 0, 47], "crossing": [1, 0, 1140], "path": [3, 0, 724], "street_lamp": [3, 0, 93]}, "est_width": {"*": [1, 0, 519]}, "power": {"tower": [61, 3, 29], "generator": [97, -2, 1]}, "leisure": {"park": [10, -1, 52], "playground": [2, 1, 31], "pitch": [21, 0, 56]}, "barrier": {"*": [10, 0, 535]}, "historic": {"*": [2, 1, 212]}, "tourism": {"*": [1, 0, 754]}, "building": {"yes": [138, -4, 422], "*": [103, -1, 775], "church": [6, 1, 28]}, "traffic_calming": {"*": [1, 0, 130]}, "natural": {"tree": [44, -1, 5]}, "tunnel": {"*": [1, 0, 1005]}, "wheelchair": {"*": [92, -25, 3]}, "tactile_paving": {"*": [23, 0, 4]}, "aeroway": {"*": [67, -3, 5]}, "place": {"town": [116, -1, 2], "locality": [1, 0, 583], "*": [7, 0, 776], "isolated_dwelling": [12, -2, 1], "hamlet": [28, 0, 119], "suburb": [9, -1, 23], "village": [39, 4, 31]}, "railway": {"*": [22, -1, 326]}, "landuse": {"residential": [24, 0, 95], "*": [34, 0, 541], "forest": [21, -1, 104], "meadow": [58, -2, 11]}, "tracktype": {"*": [27, -2, 367]}, "route": {"bicycle": [31, 3, 2], "hiking": [7, 0, 37], "tram": [3, 0, 8], "bus": [10, 2, 13], "train": [27, -3, 1], "road": [6, 0, 25]}}]