[{"Ways": [1422, -7, 26], "Nodes": [759, -5, 1638]}, {"building": {"yes": [873, -8, 1], "*": [888, -7, 1]}, "tracktype": {"*": [601, -11, 4]}, "sac_scale": {"*": [489, 4, 2]}, "mtb:scale:*": {"*": [156, -5, 8]}, "surface": {"*": [448, 13, 13]}, "height": {"*": [103, 3, 1]}, "width": {"*": [138, -7, 11]}, "boundary": {"*": [739, -7, 1]}, "tourism": {"*": [1514, 1, 1]}, "highway": {"path": [936, 2, 1], "streets|road;service;pedestrian;living_street;residential;unclassified;tertiary;secondary_link;secondary;primary_link;primary;trunk_link;trunk;motorway_link;motorway;bus_guideway": [1882, -123, 6], "footway": [439, 3, 8]}}]