[{"Ways": [544, 1, 231], "Nodes": [826, -3, 1448]}, {"bridge": {"*": [447, -5, 6]}, "amenity": {"fuel": [702, 4, 1], "drinking_water": [306, -3, 2], "place_of_worship": [1086, -5, 1], "parking": [457, -4, 8]}, "barrier": {"*": [355, 0, 4]}, "tunnel": {"*": [714, 1, 1]}, "tracktype": {"*": [1004, -18, 1]}, "ele": {"*": [424, -6, 2]}, "place": {"*": [709, 2, 2], "hamlet": [346, -2, 2]}, "railway": {"*": [704, 0, 1]}, "tourism": {"*": [1411, -11, 1]}, "highway": {"path": [942, 0, 1], "streets|road;service;pedestrian;living_street;residential;unclassified;tertiary;secondary_link;secondary;primary_link;primary;trunk_link;trunk;motorway_link;motorway;bus_guideway": [402, -1, 212]}}]