[{"Ways": [820, -9, 142], "Nodes": [1114, -5, 1039], "Relations": [356, -12, 4]}, {"shop": {"*": [463, -4, 4]}, "bridge": {"*": [478, -5, 6]}, "amenity": {"school": [347, -4, 3], "bar": [297, -2, 2], "restaurant": [421, -6, 4], "pharmacy": [683, -9, 1], "parking": [1239, -13, 2], "fuel": [731, -9, 1]}, "maxspeed": {"*": [757, -49, 1]}, "tourism": {"*": [1094, -11, 2]}, "route": {"bicycle": [83, -2, 1]}, "surface": {"*": [1266, -26, 2]}, "place": {"village": [355, 2, 3], "city": [22, -1, 1], "suburb": [98, 0, 2], "*": [346, 0, 9], "hamlet": [319, -2, 3]}, "leisure": {"park": [374, -1, 2], "playground": [246, -4, 2], "pitch": [240, -6, 4]}, "waterway": {"*": [316, -3, 6], "river": [272, -11, 1]}, "landuse": {"*": [545, 2, 6]}, "type": {"restriction": [106, 0, 2]}, "railway": {"*": [679, 2, 1]}, "highway": {"streets|road;service;pedestrian;living_street;residential;unclassified;tertiary;secondary_link;secondary;primary_link;primary;trunk_link;trunk;motorway_link;motorway;bus_guideway": [678, -10, 99], "cycleway": [524, -150, 1]}}]