[{"Ways": [1609, -5, 42], "Nodes": [1557, -14, 662]}, {"place": {"town": [181, -2, 1], "*": [982, 3, 1]}, "amenity": {"place_of_worship": [675, -4, 2], "school": [162, -2, 7], "bar": [308, -8, 2], "restaurant": [622, 4, 2], "pharmacy": [197, 2, 3], "parking": [515, -7, 9]}, "tourism": {"*": [1378, -13, 1]}, "highway": {"streets|road;service;pedestrian;living_street;residential;unclassified;tertiary;secondary_link;secondary;primary_link;primary;trunk_link;trunk;motorway_link;motorway;bus_guideway": [1196, -23, 38]}}]