[{"Ways": [840, -9, 110], "Nodes": [820, -8, 1706]}, {"shop": {"*": [547, -8, 2]}, "bridge": {"*": [444, -5, 6]}, "amenity": {"place_of_worship": [5, 0, 158], "restaurant": [714, -3, 1], "pharmacy": [364, -1, 1], "parking": [403, -5, 10]}, "maxspeed": {"*": [551, -8, 1]}, "building": {"yes": [622, -9, 4], "*": [351, -7, 38], "church": [6, 0, 23]}, "tunnel": {"*": [546, -4, 1]}, "surface": {"*": [713, -3, 5]}, "ele": {"*": [491, -2, 1]}, "note": {"*": [362, -1, 1]}, "historic": {"*": [341, -5, 2]}, "place": {"*": [528, -4, 3], "village": [307, -6, 3]}, "addr:housenumber": {"*": [195, -2, 3]}, "landuse": {"*": [529, -6, 4]}, "tourism": {"*": [589, -4, 3]}, "highway": {"stop": [69, -3, 1], "path": [661, -65, 4], "streets|road;service;pedestrian;living_street;residential;unclassified;tertiary;secondary_link;secondary;primary_link;primary;trunk_link;trunk;motorway_link;motorway;bus_guideway": [681, 3, 87], "steps": [445, -2, 1], "bus_stop": [348, -2, 2]}}]