[{"Ways": [344, -4, 716], "Nodes": [295, -2, 11642]}, {"shop": {"*": [856, -7, 1]}, "bridge": {"*": [550, 0, 4]}, "amenity": {"fuel": [300, 2, 3], "post_office": [302, -1, 1], "school": [87, -1, 11], "hospital": [75, 1, 3], "parking": [423, 0, 10]}, "building": {"yes": [431, -8, 31], "*": [439, -7, 31]}, "hgv": {"*": [35, 0, 13]}, "surface": {"*": [875, -16, 4]}, "tunnel": {"*": [620, -10, 1]}, "historic": {"*": [569, -7, 1]}, "place": {"*": [846, 65, 1]}, "leisure": {"park": [61, -2, 16], "playground": [130, -2, 3]}, "waterway": {"*": [202, -4, 15]}, "landuse": {"*": [147, 0, 79], "forest": [124, 9, 7]}, "tourism": {"*": [337, -3, 8]}, "highway": {"steps": [510, -110, 1], "streets|road;service;pedestrian;living_street;residential;unclassified;tertiary;secondary_link;secondary;primary_link;primary;trunk_link;trunk;motorway_link;motorway;bus_guideway": [276, -1, 490], "footway": [281, 3, 20]}}]