[{"Ways": [1442, -11, 57], "Nodes": [498, -3, 7033], "Relations": [268, -3, 9]}, {"building": {"yes": [1106, 142, 3], "*": [1126, 140, 3]}, "bridge": {"*": [959, -294, 2]}, "amenity": {"shelter": [132, 0, 1], "bench": [84, 0, 12]}, "route": {"bus": [47, -7, 3], "hiking": [194, 1, 1]}, "barrier": {"*": [668, -1, 2]}, "tracktype": {"*": [549, -63, 10]}, "sac_scale": {"*": [148, -4, 23]}, "wheelchair": {"*": [36, -3, 10]}, "surface": {"*": [618, -38, 15]}, "ele": {"*": [34, -1, 187]}, "note": {"*": [186, -31, 8]}, "width": {"*": [192, -31, 11]}, "historic": {"*": [400, 1, 3]}, "waterway": {"*": [284, 30, 10]}, "landuse": {"*": [1032, -1, 2]}, "tourism": {"*": [751, 3, 4]}, "boundary": {"*": [204, -6, 6]}, "highway": {"bus_stop": [321, -3, 4], "streets|road;service;pedestrian;living_street;residential;unclassified;tertiary;secondary_link;secondary;primary_link;primary;trunk_link;trunk;motorway_link;motorway;bus_guideway": [2710, -11, 5], "footway": [1508, -3, 1], "path": [332, -23, 26]}}]