[{"Ways": [1350, -4, 38], "Nodes": [1117, 0, 934]}, {"bridge": {"*": [963, 0, 1]}, "amenity": {"drinking_water": [439, -4, 1], "parking": [965, -2, 2]}, "barrier": {"*": [508, 0, 2]}, "tracktype": {"*": [588, 5, 5]}, "surface": {"*": [1201, 8, 1]}, "place": {"*": [577, -1, 3], "hamlet": [296, 0, 3]}, "leisure": {"playground": [306, -1, 1], "pitch": [316, -3, 2]}, "waterway": {"*": [616, -2, 1]}, "tourism": {"*": [208, 0, 13]}, "highway": {"bus_stop": [608, -2, 1], "streets|road;service;pedestrian;living_street;residential;unclassified;tertiary;secondary_link;secondary;primary_link;primary;trunk_link;trunk;motorway_link;motorway;bus_guideway": [1148, 12, 27], "footway": [1055, -4, 1], "path": [1083, 8, 1]}}]