[{"Ways": [2821, -23, 9], "Nodes": [4014, -29, 35]}, {"shop": {"*": [917, -9, 2]}, "addr:housenumber": {"*": [560, 132, 1]}, "amenity": {"parking": [1604, -10, 1]}, "building": {"yes": [1365, -21, 1], "*": [1047, -13, 3]}, "landuse": {"*": [1013, -19, 2]}, "tourism": {"*": [910, -13, 3]}, "highway": {"streets|road;service;pedestrian;living_street;residential;unclassified;tertiary;secondary_link;secondary;primary_link;primary;trunk_link;trunk;motorway_link;motorway;bus_guideway": [3904, -34, 1], "footway": [1221, -3, 1]}}]