[{"Ways": [640, -4, 167], "Nodes": [2141, -5, 137]}, {"shop": {"*": [192, -4, 10]}, "amenity": {"fast_food": [139, -3, 1], "school": [213, -2, 4], "bar": [120, -2, 4], "restaurant": [695, 1, 1], "hospital": [101, -4, 2], "bench": [144, -1, 1], "college": [16, 1, 5], "parking": [502, -2, 7], "post_office": [82, 0, 3], "pharmacy": [338, -5, 1], "bank": [281, -2, 1]}, "hgv": {"*": [108, -3, 1]}, "opening_hours": {"*": [29, 1, 5]}, "leisure": {"playground": [69, -1, 5]}, "highway": {"streets|road;service;pedestrian;living_street;residential;unclassified;tertiary;secondary_link;secondary;primary_link;primary;trunk_link;trunk;motorway_link;motorway;bus_guideway": [481, -2, 158], "footway": [701, 115, 2]}}]