[{"Ways": [611, -5, 343], "Nodes": [1168, -4, 1282]}, {"shop": {"*": [345, 0, 7]}, "bridge": {"*": [450, -2, 9]}, "amenity": {"fast_food": [204, 0, 1], "drinking_water": [289, 1, 4], "bar": [217, 2, 3], "restaurant": [214, -2, 9], "post_box": [288, 0, 1], "bench": [100, -6, 9], "parking": [465, 31, 11], "fuel": [246, -2, 5], "place_of_worship": [191, -3, 14], "post_office": [152, -2, 3], "bank": [426, -3, 1]}, "maxspeed": {"*": [1012, -5, 1]}, "building": {"yes": [1149, -9, 2], "*": [1169, -11, 2]}, "barrier": {"*": [323, -3, 9]}, "tunnel": {"*": [250, -1, 10]}, "sac_scale": {"*": [261, -4, 11]}, "mtb:scale:*": {"*": [365, 52, 3]}, "surface": {"*": [628, -5, 14]}, "width": {"*": [638, -9, 1]}, "tactile_paving": {"*": [105, 0, 1]}, "historic": {"*": [126, 2, 12]}, "place": {"*": [1146, 0, 1]}, "leisure": {"park": [541, -7, 1], "playground": [153, 1, 3], "pitch": [409, -4, 2]}, "railway": {"*": [196, 1, 15]}, "waterway": {"*": [707, 29, 1]}, "landuse": {"*": [1219, 0, 1]}, "tourism": {"*": [100, 1, 37]}, "boundary": {"*": [336, 0, 3]}, "highway": {"streets|road;service;pedestrian;living_street;residential;unclassified;tertiary;secondary_link;secondary;primary_link;primary;trunk_link;trunk;motorway_link;motorway;bus_guideway": [676, 3, 128], "footway": [130, -3, 72], "bus_stop": [177, -12, 11], "steps": [39, 0, 51], "crossing": [198, 11, 3], "path": [276, 1, 32]}}]