[{"Ways": [1741, -3, 34], "Nodes": [863, 0, 2442]}, {"shop": {"*": [1065, -2, 1]}, "amenity": {"drinking_water": [302, -2, 4], "place_of_worship": [986, 0, 1], "pharmacy": [696, -3, 1], "parking": [1531, 2, 1]}, "tracktype": {"*": [432, 14, 14]}, "sac_scale": {"*": [422, 61, 5]}, "surface": {"*": [1323, -7, 2]}, "ele": {"*": [770, -1, 1]}, "width": {"*": [733, -5, 1]}, "historic": {"*": [824, -4, 1]}, "place": {"*": [1044, -3, 1], "locality": [312, 0, 1]}, "leisure": {"playground": [513, 1, 1]}, "boundary": {"*": [293, 3, 4]}, "tourism": {"*": [789, -1, 3]}, "highway": {"path": [1345, 5, 1], "streets|road;service;pedestrian;living_street;residential;unclassified;tertiary;secondary_link;secondary;primary_link;primary;trunk_link;trunk;motorway_link;motorway;bus_guideway": [2380, -1, 6]}}]