[{"Ways": [2820, -25, 8], "Nodes": [4669, -31, 13]}, {"building": {"yes": [1060, -4, 2], "*": [1076, -7, 2]}, "amenity": {"post_office": [406, 0, 1], "school": [1076, -11, 1], "restaurant": [996, -5, 1]}, "power": {"generator": [34, -2, 1]}, "leisure": {"playground": [406, -3, 1]}, "surface": {"*": [1602, -19, 1]}, "highway": {"streets|road;service;pedestrian;living_street;residential;unclassified;tertiary;secondary_link;secondary;primary_link;primary;trunk_link;trunk;motorway_link;motorway;bus_guideway": [2510, -11, 5]}}]