[{"Ways": [694, -10, 214], "Nodes": [331, -5, 10949]}, {"amenity": {"drinking_water": [45, -1, 36]}, "maxspeed": {"*": [696, -2, 1]}, "barrier": {"*": [700, -13, 1]}, "sac_scale": {"*": [697, -17, 1]}, "surface": {"*": [653, -26, 11]}, "boundary": {"*": [403, -3, 2]}, "landuse": {"*": [623, -54, 5]}, "tracktype": {"*": [80, 3, 158]}, "highway": {"path": [407, 11, 16], "streets|road;service;pedestrian;living_street;residential;unclassified;tertiary;secondary_link;secondary;primary_link;primary;trunk_link;trunk;motorway_link;motorway;bus_guideway": [1847, -134, 11]}}]