[{"Ways": [1285, -3, 37], "Nodes": [1292, -7, 600]}, {"amenity": {"parking": [921, 2, 2]}, "sac_scale": {"*": [362, 3, 4]}, "surface": {"*": [918, -36, 3]}, "width": {"*": [554, -8, 1]}, "boundary": {"*": [720, -8, 1]}, "highway": {"steps": [521, -6, 1], "streets|road;service;pedestrian;living_street;residential;unclassified;tertiary;secondary_link;secondary;primary_link;primary;trunk_link;trunk;motorway_link;motorway;bus_guideway": [1350, 33, 16], "footway": [564, 3, 5], "path": [346, 0, 13]}}]