[{"Ways": [1204, -55, 80], "Nodes": [446, -7, 7606]}, {"addr:housenumber": {"*": [608, -9, 1]}, "bridge": {"*": [576, -40, 5]}, "amenity": {"place_of_worship": [783, 0, 2], "restaurant": [350, 1, 5], "pharmacy": [323, 2, 2], "parking": [1291, -9, 2], "post_office": [475, -2, 1], "cafe": [124, 1, 6], "bank": [471, 1, 1]}, "building": {"yes": [785, -6, 8], "*": [797, -6, 8]}, "historic": {"*": [763, -8, 1]}, "place": {"village": [12, 0, 83], "suburb": [110, -1, 2], "*": [76, -5, 90], "hamlet": [275, -22, 5]}, "highway": {"steps": [385, 1, 3], "streets|road;service;pedestrian;living_street;residential;unclassified;tertiary;secondary_link;secondary;primary_link;primary;trunk_link;trunk;motorway_link;motorway;bus_guideway": [1043, -62, 51], "footway": [501, 2, 9]}}]